jpfiddle_extension/__init__.py
jpfiddle_extension/_version.py
jpfiddle_extension-0.1.12.data/data/share/jupyter/labextensions/jpfiddle_extension/package.json
jpfiddle_extension-0.1.12.data/data/share/jupyter/labextensions/jpfiddle_extension/static/509.1a8d224c67c095cd5015.js
jpfiddle_extension-0.1.12.data/data/share/jupyter/labextensions/jpfiddle_extension/static/728.151b68248be6f9ed2608.js
jpfiddle_extension-0.1.12.data/data/share/jupyter/labextensions/jpfiddle_extension/static/remoteEntry.104189d8e0dcd2495538.js
jpfiddle_extension-0.1.12.data/data/share/jupyter/labextensions/jpfiddle_extension/static/style.js
jpfiddle_extension-0.1.12.data/data/share/jupyter/labextensions/jpfiddle_extension/static/third-party-licenses.json
jpfiddle_extension-0.1.12.data/data/share/jupyter/labextensions/jpfiddle_extension/install.json
jpfiddle_extension-0.1.12.dist-info/METADATA
jpfiddle_extension-0.1.12.dist-info/WHEEL
jpfiddle_extension-0.1.12.dist-info/licenses/LICENSE
jpfiddle_extension-0.1.12.dist-info/RECORD
